pyscaffoldext/dsproject/__init__.py
pyscaffoldext/dsproject/extension.py
pyscaffoldext/dsproject/templates/Dockerfile.template
pyscaffoldext/dsproject/templates/__init__.py
pyscaffoldext/dsproject/templates/environment_yml.template
pyscaffoldext/dsproject/templates/gitignore_all.template
pyscaffoldext/dsproject/templates/gitignore_data.template
pyscaffoldext/dsproject/templates/readme_md.template
pyscaffoldext/dsproject/templates/template_ipynb.template
pyscaffoldext/dsproject/templates/train_model_py.template
pyscaffoldext_dsproject-0.7.2.dist-info/AUTHORS.rst
pyscaffoldext_dsproject-0.7.2.dist-info/LICENSE.txt
pyscaffoldext_dsproject-0.7.2.dist-info/METADATA
pyscaffoldext_dsproject-0.7.2.dist-info/WHEEL
pyscaffoldext_dsproject-0.7.2.dist-info/entry_points.txt
pyscaffoldext_dsproject-0.7.2.dist-info/top_level.txt
pyscaffoldext_dsproject-0.7.2.dist-info/RECORD
