Metadata-Version: 2.1
Name: pyscaffoldext-dsproject
Version: 0.7.2
Summary: PyScaffold extension for Data Science projects
Home-page: https://github.com/pyscaffold/pyscaffoldext-dsproject
Author: Florian Wilhelm
Author-email: florian.wilhelm@gmail.com
License: MIT
Project-URL: Documentation, https://pyscaffold.org/
Project-URL: Source, https://github.com/pyscaffold/pyscaffoldext-dsproject/
Project-URL: Tracker, https://github.com/pyscaffold/pyscaffoldext-dsproject/issues
Project-URL: Download, https://pypi.org/project/PyScaffoldext-dsproject/#files
Project-URL: Changelog, https://github.com/pyscaffold/pyscaffoldext-dsproject/blob/master/CHANGELOG.rst
Project-URL: Twitter, https://twitter.com/PyScaffold
Platform: any
Classifier: Development Status :: 4 - Beta
Classifier: Topic :: Utilities
Classifier: Programming Language :: Python
Classifier: Programming Language :: Python :: 3
Classifier: Programming Language :: Python :: 3 :: Only
Classifier: Environment :: Console
Classifier: Intended Audience :: Developers
Classifier: License :: OSI Approved :: MIT License
Classifier: Operating System :: POSIX :: Linux
Classifier: Operating System :: Unix
Classifier: Operating System :: MacOS
Classifier: Operating System :: Microsoft :: Windows
License-File: LICENSE.txt
License-File: AUTHORS.rst
Requires-Dist: pyscaffold (<5.0a0,>=4.0.1)
Requires-Dist: pyscaffoldext-markdown (<1.0a0,>=0.4.1)
Requires-Dist: importlib-metadata ; python_version < "3.8"
Provides-Extra: testing
Requires-Dist: tox ; extra == 'testing'
Requires-Dist: pre-commit ; extra == 'testing'
Requires-Dist: setuptools-scm ; extra == 'testing'
Requires-Dist: virtualenv ; extra == 'testing'
Requires-Dist: configupdater ; extra == 'testing'
Requires-Dist: pytest ; extra == 'testing'
Requires-Dist: pytest-cov ; extra == 'testing'
Requires-Dist: pytest-xdist ; extra == 'testing'
